LICENSE
README.md
setup.py
cryptwentyone/__init__.py
cryptwentyone.egg-info/PKG-INFO
cryptwentyone.egg-info/SOURCES.txt
cryptwentyone.egg-info/dependency_links.txt
cryptwentyone.egg-info/top_level.txt
cryptwentyone/Hash/Hash.py
cryptwentyone/Hash/MD5.py
cryptwentyone/Hash/SHA1.py
cryptwentyone/Hash/SHA2.py
cryptwentyone/Hash/__init__.py